Metadata-Version: 1.0
Name: mmmnnn-distributions
Version: 99.2
Summary: Gaussian distributions
Home-page: UNKNOWN
Author: Weerachai Srisingchai
Author-email: No@mal.com
License: UNKNOWN
Platform: UNKNOWN
